origen/__init__.py
origen/ai/__init__.py
origen/ai/ecl.cpython-38-x86_64-linux-gnu.so
origen_ai_ecl-0.2.11.dist-info/METADATA
origen_ai_ecl-0.2.11.dist-info/WHEEL
origen_ai_ecl-0.2.11.dist-info/RECORD
