Metadata-Version: 2.1
Name: origen-ai-ecl
Version: 0.2.11
Summary: 
Author: Luis Arce
Author-email: luis@origen.ai
Requires-Python: >=3.8,<4.0
Classifier: Programming Language :: Python :: 3
Classifier: Programming Language :: Python :: 3.8
Classifier: Programming Language :: Python :: 3.9
Classifier: Programming Language :: Python :: 3.10
Classifier: Programming Language :: Python :: 3.11
Requires-Dist: pybind11[global] (>=2.10.4,<3.0.0)
